{"können":1,"wawartet":1,"die":2,"Jetz":1,"gibt":1,"deutlich":1,"alles":1,"nun":1,"finaler":1,"Wenn":1,"ist":2,"manche":1,"höglichkeit":1,"sich":1,"ich":1,"funktionie":1,"mehr":1,"TestTestTest":3,"Wirtschaftsminister":1,"tut":1,"hatteswirtschaftsminister-":1,"Test":2,"jetzt":2,"Warum":1,"testTestT":1,"aa":2,"aber":1,"funktionieren":7,"hatteswirtschaftsminister":1,"textext":1,"nicht":1,"es":7,"eigentlich":1,"probiere":1,"zumindest":2,"nein":1,"Jetzt":2,"angezeigt":1,"ohneenende":1,"wenn":1,"funktioniere":1,"warum":4,"Modernisierung":1,"zu":3,"sollte":1,"darum":1,"sein":1,"aaaaaaaaaaa":1,"echte":1,"gut":2,"scheint":3,"Möglichkeit":1,"alle":1,"nochmal":3,"gerade":1,"verfollständigen":1,"ein":5,"manchmal":1,"finfach":2,"Tests":1,"Es":1,"testTestTest":3,"besser":1,"ob":1,"Irgendwie":1,"noch":2,"keine":1,"wieder":3,"geht":1,"Wörter":3,"hier":1,"wollen":1,"überstanden":1,"funktionierten":1,"oderern":1,"aaaaaaaaa":1,"Versuch":3,"sehr":1,"einfach":1,"also":1,"malaus":1,"aaaaaaaaaaaaaaaaaaaaaa":1,"oder":1,"eine":1,"manchma3":1,"konktionieren":1,"neuer":1,"Das":1,"Also":2,"kfunktionieren":1,"aaaaaaaaaa":1,"istdas":1,"werden":3}